pamqp/__init__.py
pamqp/base.py
pamqp/body.py
pamqp/commands.py
pamqp/common.py
pamqp/constants.py
pamqp/decode.py
pamqp/encode.py
pamqp/exceptions.py
pamqp/frame.py
pamqp/header.py
pamqp/heartbeat.py
pamqp/py.typed
pamqp-3.3.0.dist-info/LICENSE
pamqp-3.3.0.dist-info/METADATA
pamqp-3.3.0.dist-info/WHEEL
pamqp-3.3.0.dist-info/top_level.txt
pamqp-3.3.0.dist-info/zip-safe
pamqp-3.3.0.dist-info/RECORD
