Metadata-Version: 2.1
Name: pamqp
Version: 3.3.0
Summary: RabbitMQ Focused AMQP low-level library
Home-page: https://github.com/gmr/pamqp
Author: Gavin M. Roy
Author-email: gavinmroy@gmail.com
License: BSD 3-Clause License
Project-URL: Bug Tracker, https://github.com/gmr/pamqp/issues
Project-URL: Documentation, https://pamqp.readthedocs.io
Project-URL: Source Code, https://github.com/gmr/pamqp/
Keywords: amqp,rabbitmq
Classifier: Development Status :: 5 - Production/Stable
Classifier: Intended Audience :: Developers
Classifier: License :: OSI Approved :: BSD License
Classifier: Natural Language :: English
Classifier: Operating System :: OS Independent
Classifier: Programming Language :: Python :: 3
Classifier: Programming Language :: Python :: 3.7
Classifier: Programming Language :: Python :: 3.8
Classifier: Programming Language :: Python :: 3.9
Classifier: Programming Language :: Python :: 3.10
Classifier: Programming Language :: Python :: 3.11
Classifier: Programming Language :: Python :: 3.12
Classifier: Programming Language :: Python :: 3 :: Only
Classifier: Topic :: Communications
Classifier: Topic :: Internet
Classifier: Topic :: Software Development
Classifier: Typing :: Typed
Requires-Python: >=3.7
Provides-Extra: codegen
Provides-Extra: testing
License-File: LICENSE
